{
  "syncFolderName": true,
  "ctrlKey": true,
  "altKey": false,
  "hideFolderNote": true,
  "templatePath": "",
  "autoCreate": false,
  "autoCreateFocusFiles": true,
  "autoCreateForAttachmentFolder": false,
  "autoCreateForFiles": false,
  "enableCollapsing": false,
  "excludeFolders": [],
  "whitelistFolders": [],
  "showDeleteConfirmation": true,
  "underlineFolder": true,
  "stopWhitespaceCollapsing": true,
  "underlineFolderInPath": true,
  "openFolderNoteOnClickInPath": true,
  "openInNewTab": false,
  "focusExistingTab": false,
  "oldFolderNoteName": "{{folder_name}}",
  "folderNoteName": "{{folder_name}}",
  "folderNoteType": ".md",
  "disableFolderHighlighting": false,
  "newFolderNoteName": "{{folder_name}}",
  "storageLocation": "insideFolder",
  "syncDelete": false,
  "showRenameConfirmation": true,
  "defaultOverview": {
    "id": "",
    "folderPath": "",
    "title": "{{folderName}} overview",
    "showTitle": false,
    "depth": 3,
    "includeTypes": [
      "folder",
      "markdown"
    ],
    "style": "list",
    "disableFileTag": false,
    "sortBy": "name",
    "sortByAsc": true,
    "showEmptyFolders": false,
    "onlyIncludeSubfolders": false,
    "storeFolderCondition": true,
    "showFolderNotes": false,
    "disableCollapseIcon": true,
    "alwaysCollapse": false,
    "autoSync": true,
    "allowDragAndDrop": true,
    "hideLinkList": true,
    "hideFolderOverview": false,
    "useActualLinks": false,
    "fmtpIntegration": false,
    "titleSize": 1,
    "isInCallout": false
  },
  "useSubmenus": true,
  "syncMove": true,
  "frontMatterTitle": {
    "enabled": false,
    "explorer": true,
    "path": true
  },
  "settingsTab": "general",
  "supportedFileTypes": [
    "md",
    "canvas"
  ],
  "boldName": false,
  "boldNameInPath": false,
  "cursiveName": false,
  "cursiveNameInPath": false,
  "disableOpenFolderNoteOnClick": false,
  "openByClick": true,
  "openWithCtrl": false,
  "openWithAlt": false,
  "excludeFolderDefaultSettings": {
    "type": "folder",
    "path": "",
    "id": "e8ba2b7d-1613-4cc4-8462-06b5c77b58c0",
    "subFolders": true,
    "disableSync": true,
    "disableAutoCreate": true,
    "disableFolderNote": false,
    "enableCollapsing": false,
    "position": 0,
    "excludeFromFolderOverview": false,
    "string": "",
    "hideInSettings": false,
    "detached": false,
    "showFolderNote": false
  },
  "excludePatternDefaultSettings": {
    "type": "pattern",
    "path": "",
    "id": "94d3022f-d1f9-4da5-b281-e99b8387c732",
    "subFolders": true,
    "disableSync": true,
    "disableAutoCreate": true,
    "disableFolderNote": false,
    "enableCollapsing": false,
    "position": 0,
    "excludeFromFolderOverview": false,
    "string": "",
    "hideInSettings": false,
    "detached": false,
    "showFolderNote": false
  },
  "hideCollapsingIcon": false,
  "hideCollapsingIconForEmptyFolders": false,
  "tabManagerEnabled": true,
  "ignoreAttachmentFolder": true,
  "deleteFilesAction": "trash",
  "openSidebar": {
    "mobile": false,
    "desktop": true
  },
  "highlightFolder": true,
  "persistentSettingsTab": {
    "afterRestart": true,
    "afterChangingTab": true
  },
  "firstTimeInsertOverview": false,
  "fvGlobalSettings": {
    "autoUpdateLinks": false
  }
}